ai_ledger/__init__.py
ai_ledger/account.py
ai_ledger/bootstrap_registry.py
ai_ledger/canonical_json.py
ai_ledger/cli.py
ai_ledger/crypto.py
ai_ledger/demo.py
ai_ledger/discovery.py
ai_ledger/distributed_validator.py
ai_ledger/global_discovery.py
ai_ledger/keygen.py
ai_ledger/llm.py
ai_ledger/network_node.py
ai_ledger/node.py
ai_ledger/p2p.py
ai_ledger/params.py
ai_ledger/quorum.py
ai_ledger/storage.py
ai_ledger/storage_utils.py
ai_ledger/transaction.py
ai_ledger/validator.py
ai_ledger/verify.py
ai_ledger/tests/__init__.py
ai_ledger/tests/test_canonical.py
ai_ledger/tests/test_llm_safety.py
ai_ledger/tests/test_quorum.py
ai_ledger/tests/test_replay.py
blockless_ai_ledger-1.0.4.dist-info/METADATA
blockless_ai_ledger-1.0.4.dist-info/WHEEL
blockless_ai_ledger-1.0.4.dist-info/entry_points.txt
blockless_ai_ledger-1.0.4.dist-info/top_level.txt
blockless_ai_ledger-1.0.4.dist-info/RECORD
