Metadata-Version: 2.4
Name: blockless-ai-ledger
Version: 1.0.4
Summary: 🌍 Global AI-powered blockchain - Join the worldwide decentralized network instantly
Home-page: https://github.com/netharalabs/blockless
Author: Nethara Labs
Author-email: Nethara Labs <contact@netharalabs.com>
Project-URL: Homepage, https://github.com/netharalabs/blockless
Project-URL: Bug Tracker, https://github.com/netharalabs/blockless/issues
Project-URL: Documentation, https://github.com/netharalabs/blockless
Project-URL: Source, https://github.com/netharalabs/blockless
Keywords: blockchain,ai,distributed-ledger,cryptocurrency,validation,decentralized,global,consensus
Platform: any
Classifier: Development Status :: 5 - Production/Stable
Classifier: Intended Audience :: Developers
Classifier: Intended Audience :: Financial and Insurance Industry
Classifier: Topic :: Office/Business :: Financial
Classifier: Topic :: Scientific/Engineering :: Artificial Intelligence
Classifier: Topic :: System :: Distributed Computing
Classifier: Topic :: Internet :: WWW/HTTP :: HTTP Servers
Classifier: Programming Language :: Python :: 3
Classifier: Programming Language :: Python :: 3.11
Classifier: Programming Language :: Python :: 3.12
Classifier: Operating System :: OS Independent
Classifier: Operating System :: POSIX :: Linux
Classifier: Operating System :: MacOS
Classifier: Operating System :: Microsoft :: Windows
Requires-Python: >=3.11
Requires-Dist: fastapi>=0.68.0
Requires-Dist: uvicorn[standard]>=0.15.0
Requires-Dist: pydantic>=1.8.0
Requires-Dist: typer>=0.4.0
Requires-Dist: aiohttp>=3.8.0
Requires-Dist: cryptography>=3.4.8
Requires-Dist: openai>=1.0.0
Requires-Dist: colorama>=0.4.4
Requires-Dist: pytest>=6.0.0
Requires-Dist: pytest-asyncio>=0.18.0
Requires-Dist: PyNaCl>=1.5.0
Requires-Dist: portalocker>=2.7.0
Requires-Dist: psutil>=5.9.0
Requires-Dist: loguru>=0.7.0
Requires-Dist: blake3>=0.3.0
Provides-Extra: openai
Requires-Dist: openai>=1.0.0; extra == "openai"
Provides-Extra: dev
Requires-Dist: pytest>=7.0; extra == "dev"
Requires-Dist: pytest-asyncio>=0.21.0; extra == "dev"
Requires-Dist: black>=23.0; extra == "dev"
Requires-Dist: ruff>=0.1.0; extra == "dev"
Dynamic: author
Dynamic: home-page
Dynamic: platform
Dynamic: requires-python
